taki_graphics/__init__.py
taki_graphics/config.py
taki_graphics/exceptions.py
taki_graphics/locations_config.py
taki_graphics/render.py
taki_graphics/taki_graphics.py
taki_graphics/utils.py
taki_graphics/assets/BACK.png
taki_graphics/assets/BLUE.png
taki_graphics/assets/BLUE_1.png
taki_graphics/assets/BLUE_3.png
taki_graphics/assets/BLUE_4.png
taki_graphics/assets/BLUE_5.png
taki_graphics/assets/BLUE_6.png
taki_graphics/assets/BLUE_7.png
taki_graphics/assets/BLUE_8.png
taki_graphics/assets/BLUE_9.png
taki_graphics/assets/BLUE_ADD_TURN.png
taki_graphics/assets/BLUE_PLUS.png
taki_graphics/assets/BLUE_PLUS2.png
taki_graphics/assets/BLUE_REVERSE.png
taki_graphics/assets/BLUE_SKIP.png
taki_graphics/assets/BLUE_TAKI.png
taki_graphics/assets/BREAK3.png
taki_graphics/assets/GRAY_SWAP.png
taki_graphics/assets/GREEN.png
taki_graphics/assets/GREEN_1.png
taki_graphics/assets/GREEN_3.png
taki_graphics/assets/GREEN_4.png
taki_graphics/assets/GREEN_5.png
taki_graphics/assets/GREEN_6.png
taki_graphics/assets/GREEN_7.png
taki_graphics/assets/GREEN_8.png
taki_graphics/assets/GREEN_9.png
taki_graphics/assets/GREEN_ADD_TURN.png
taki_graphics/assets/GREEN_PLUS.png
taki_graphics/assets/GREEN_PLUS2.png
taki_graphics/assets/GREEN_REVERSE.png
taki_graphics/assets/GREEN_SKIP.png
taki_graphics/assets/GREEN_TAKI.png
taki_graphics/assets/KING.png
taki_graphics/assets/PLUS3.png
taki_graphics/assets/RED.png
taki_graphics/assets/RED_1.png
taki_graphics/assets/RED_3.png
taki_graphics/assets/RED_4.png
taki_graphics/assets/RED_5.png
taki_graphics/assets/RED_6.png
taki_graphics/assets/RED_7.png
taki_graphics/assets/RED_8.png
taki_graphics/assets/RED_9.png
taki_graphics/assets/RED_ADD_TURN.png
taki_graphics/assets/RED_PLUS.png
taki_graphics/assets/RED_PLUS2.png
taki_graphics/assets/RED_REVERSE.png
taki_graphics/assets/RED_SKIP.png
taki_graphics/assets/RED_TAKI.png
taki_graphics/assets/WILD_COLOR.png
taki_graphics/assets/WILD_TAKI.png
taki_graphics/assets/YELLOW.png
taki_graphics/assets/YELLOW_1.png
TakiGraphics-0.4.1.dist-info/METADATA
TakiGraphics-0.4.1.dist-info/WHEEL
TakiGraphics-0.4.1.dist-info/top_level.txt
TakiGraphics-0.4.1.dist-info/RECORD
