Metadata-Version: 2.1
Name: TakiGraphics
Version: 0.4.1
Summary: A graphical interface for the Taki card game using Pygame.
Requires-Python: >=3.6
Requires-Dist: pygame
